[
{"url": ["https://pta.trunojoyo.ac.id/welcome/detail/060411100755"]},
{"url": ["https://pta.trunojoyo.ac.id/welcome/detail/080411100102"]},
{"url": ["https://pta.trunojoyo.ac.id/welcome/detail/050411100662"]},
{"url": ["https://pta.trunojoyo.ac.id/welcome/detail/080411100014"]},
{"url": ["https://pta.trunojoyo.ac.id/welcome/detail/080411100041"]},
{"url": ["https://pta.trunojoyo.ac.id/welcome/detail/080411100012"]},
{"url": ["https://pta.trunojoyo.ac.id/welcome/detail/070411100170"]},
{"url": ["https://pta.trunojoyo.ac.id/welcome/detail/050411100558"]},
{"url": ["https://pta.trunojoyo.ac.id/welcome/detail/070411100133"]},
{"url": ["https://pta.trunojoyo.ac.id/welcome/detail/080411100010"]},
{"url": ["https://pta.trunojoyo.ac.id/welcome/detail/080411100086"]},
{"url": ["https://pta.trunojoyo.ac.id/welcome/detail/080411100052"]},
{"url": ["https://pta.trunojoyo.ac.id/welcome/detail/060411100818"]},
{"url": ["https://pta.trunojoyo.ac.id/welcome/detail/080411100125"]},
{"url": ["https://pta.trunojoyo.ac.id/welcome/detail/080411100029"]},
{"url": ["https://pta.trunojoyo.ac.id/welcome/detail/070411100007"]},
{"url": ["https://pta.trunojoyo.ac.id/welcome/detail/070411100126"]},
{"url": ["https://pta.trunojoyo.ac.id/welcome/detail/070411100109"]},
{"url": ["https://pta.trunojoyo.ac.id/welcome/detail/080411100083"]},
{"url": ["https://pta.trunojoyo.ac.id/welcome/detail/070411100092"]},
{"url": ["https://pta.trunojoyo.ac.id/welcome/detail/040411100468"]},
{"url": ["https://pta.trunojoyo.ac.id/welcome/detail/040411100476"]},
{"url": ["https://pta.trunojoyo.ac.id/welcome/detail/040411100480"]},
{"url": ["https://pta.trunojoyo.ac.id/welcome/detail/070411100070"]},
{"url": ["https://pta.trunojoyo.ac.id/welcome/detail/080411100115"]},
{"url": ["https://pta.trunojoyo.ac.id/welcome/detail/070411100124"]},
{"url": ["https://pta.trunojoyo.ac.id/welcome/detail/070411100072"]},
{"url": ["https://pta.trunojoyo.ac.id/welcome/detail/070411100152"]},
{"url": ["https://pta.trunojoyo.ac.id/welcome/detail/070411100114"]},
{"url": ["https://pta.trunojoyo.ac.id/welcome/detail/070411100036"]},
{"url": ["https://pta.trunojoyo.ac.id/welcome/detail/070411100083"]},
{"url": ["https://pta.trunojoyo.ac.id/welcome/detail/070411100102"]},
{"url": ["https://pta.trunojoyo.ac.id/welcome/detail/050411100538"]},
{"url": ["https://pta.trunojoyo.ac.id/welcome/detail/080411100011"]},
{"url": ["https://pta.trunojoyo.ac.id/welcome/detail/070411100158"]},
{"url": ["https://pta.trunojoyo.ac.id/welcome/detail/080411100002"]},
{"url": ["https://pta.trunojoyo.ac.id/welcome/detail/080411100062"]},
{"url": ["https://pta.trunojoyo.ac.id/welcome/detail/070411100155"]},
{"url": ["https://pta.trunojoyo.ac.id/welcome/detail/050411100614"]},
{"url": ["https://pta.trunojoyo.ac.id/welcome/detail/050411100566"]},
{"url": ["https://pta.trunojoyo.ac.id/welcome/detail/050411100651"]},
{"url": ["https://pta.trunojoyo.ac.id/welcome/detail/070411100119"]},
{"url": ["https://pta.trunojoyo.ac.id/welcome/detail/080411100113"]},
{"url": ["https://pta.trunojoyo.ac.id/welcome/detail/070411100136"]},
{"url": ["https://pta.trunojoyo.ac.id/welcome/detail/070411100023"]},
{"url": ["https://pta.trunojoyo.ac.id/welcome/detail/070411100120"]},
{"url": ["https://pta.trunojoyo.ac.id/welcome/detail/070411100143"]},
{"url": ["https://pta.trunojoyo.ac.id/welcome/detail/070411100037"]},
{"url": ["https://pta.trunojoyo.ac.id/welcome/detail/070411100079"]},
{"url": ["https://pta.trunojoyo.ac.id/welcome/detail/070411100050"]},
{"url": ["https://pta.trunojoyo.ac.id/welcome/detail/070411100029"]},
{"url": ["https://pta.trunojoyo.ac.id/welcome/detail/060411100824"]},
{"url": ["https://pta.trunojoyo.ac.id/welcome/detail/060411100772"]},
{"url": ["https://pta.trunojoyo.ac.id/welcome/detail/080411100001"]},
{"url": ["https://pta.trunojoyo.ac.id/welcome/detail/060411100801"]},
{"url": ["https://pta.trunojoyo.ac.id/welcome/detail/080411100078"]},
{"url": ["https://pta.trunojoyo.ac.id/welcome/detail/070411100081"]},
{"url": ["https://pta.trunojoyo.ac.id/welcome/detail/070411100042"]},
{"url": ["https://pta.trunojoyo.ac.id/welcome/detail/070411100129"]},
{"url": ["https://pta.trunojoyo.ac.id/welcome/detail/080411100003"]}
]